ldsagrader/__init__.py
ldsagrader/ldsagrader.py
ldsagrader/utils.py
ldsagrader/preprocessors/__init__.py
ldsagrader/preprocessors/forbidhiddentests.py
ldsagrader-0.5.7.dist-info/AUTHORS.rst
ldsagrader-0.5.7.dist-info/LICENSE
ldsagrader-0.5.7.dist-info/METADATA
ldsagrader-0.5.7.dist-info/WHEEL
ldsagrader-0.5.7.dist-info/entry_points.txt
ldsagrader-0.5.7.dist-info/top_level.txt
ldsagrader-0.5.7.dist-info/RECORD
