Metadata-Version: 2.1
Name: ldsagrader
Version: 0.5.7
Summary: Application to grade LDSA notebooks
Home-page: https://github.com/hcastilho/ldsagrader
Author: Hugo Castilho
Author-email: hcastilho@lisbondatascience.org
License: MIT license
Keywords: ldsagrader
Platform: UNKNOWN
Classifier: Development Status :: 2 - Pre-Alpha
Classifier: Intended Audience :: Developers
Classifier: License :: OSI Approved :: MIT License
Classifier: Natural Language :: English
Classifier: Programming Language :: Python :: 3
Classifier: Programming Language :: Python :: 3.4
Classifier: Programming Language :: Python :: 3.5
Classifier: Programming Language :: Python :: 3.6
Classifier: Programming Language :: Python :: 3.7
Requires-Dist: Click
Requires-Dist: nbgrader
Requires-Dist: requests
